[
  {
    "0": {
      "0": {
        "0": [
          [
            45.40270760000001,
            -75.68795
          ]
        ],
        "0.4": [
          [
            45.40630667452247,
            -75.68795
          ],
          "min order - 20.0"
        ],
        "0.8": [
          [
            45.41350481673435,
            -75.68795
          ],
          "min order - 20.0"
        ],
        "1.2000000000000002": [
          [
            45.424302012969655,
            -75.68795
          ],
          "min order - 20.0"
        ],
        "1.6": [
          [
            45.438698242729615,
            -75.68795
          ],
          "min order - 20.0"
        ]
      },
      "20": {
        "0": [
          [
            45.402707600000014,
            -75.68795
          ]
        ],
        "0.4": [
          [
            45.40608961046804,
            -75.68620250034415
          ],
          "min order - 20.0"
        ],
        "0.8": [
          [
            45.41285359862607,
            -75.68270708386031
          ],
          "min order - 20.0"
        ],
        "1.2000000000000002": [
          [
            45.42299952563268,
            -75.67746302008551
          ],
          "min order - 20.0"
        ],
        "1.6": [
          [
            45.43652734656437,
            -75.67046926460179
          ],
          "min order - 20.0"
        ],
        "2.0": [
          [
            45.45343701039698,
            -75.66172445809252
          ],
          "min order - 20.0"
        ]
      },
      "40": {
        "0": [
          [
            45.402707600000014,
            -75.68795
          ]
        ],
        "0.4": [
          [
            45.40546460402995,
            -75.68466581115213
          ],
          "min order - 20.0"
        ],
        "0.8": [
          [
            45.41097851362499,
            -75.67809679436444
          ],
          "min order - 20.0"
        ],
        "1.2000000000000002": [
          [
            45.41924922622488,
            -75.66824183073076
          ],
          "min order - 20.0"
        ],
        "1.6": [
          [
            45.43027663511994,
            -75.65509932071943
          ],
          "min order - 20.0"
        ],
        "2.0": [
          [
            45.444060629397015,
            -75.63866718301333
          ],
          "min order - 20.0"
        ],
        "2.4": [
          [
            45.46060109388534,
            -75.61894285300014
          ],
          "min order - 20.0"
        ]
      },
      "60": {
        "0": [
          [
            45.40270760000001,
            -75.68795
          ]
        ],
        "0.4": [
          [
            45.404507051847425,
            -75.68352529908572
          ],
          "min order - 20.0"
        ],
        "0.8": [
          [
            45.40810578240128,
            -75.67467533532903
          ],
          "min order - 20.0"
        ],
        "1.2000000000000002": [
          [
            45.413503616710905,
            -75.66139912511508
          ],
          "min order - 20.0"
        ],
        "1.6": [
          [
            45.42070037795189,
            -75.643695262718
          ],
          "min order - 20.0"
        ],
        "2.0": [
          [
            45.42969588736209,
            -75.62156191967705
          ],
          "min order - 20.0"
        ],
        "2.4": [
          [
            45.44048996417739,
            -75.59499684397298
          ],
          "min order - 20.0"
        ]
      }
    }
  },
  {
    "0": {
      "72": {
        "0": [
          [
            45.4027076,
            -75.68795
          ]
        ],
        "0.4": [
          [
            45.40381967208289,
            -75.68309091666715
          ],
          "min order - 20.0"
        ],
        "0.8": [
          [
            45.40604360886611,
            -75.67337236866419
          ],
          "min order - 20.0"
        ],
        "1.2000000000000002": [
          [
            45.40937920223899,
            -75.65879368860148
          ],
          "min order - 20.0"
        ],
        "1.6": [
          [
            45.41382624331507,
            -75.63935392290763
          ],
          "min order - 20.0"
        ],
        "2.0": [
          [
            45.41938452238447,
            -75.61505183161667
          ],
          "min order - 20.0"
        ],
        "2.4": [
          [
            45.426053828866046,
            -75.58588588807176
          ],
          "min order - 20.0"
        ],
        "2.8": [
          [
            45.433833951259736,
            -75.55185427854524
          ],
          "min order - 20.0"
        ]
      },
      "92": {
        "0": [
          [
            45.40270760000001,
            -75.68795
          ]
        ],
        "0.4": [
          [
            45.40258187994901,
            -75.68284408128231
          ],
          "min order - 20.0"
        ],
        "0.8": [
          [
            45.40233021160114,
            -75.67263228916518
          ],
          "min order - 20.0"
        ],
        "1.2000000000000002": [
          [
            45.40195236671166,
            -75.6573147030412
          ],
          "min order - 20.0"
        ],
        "1.6": [
          [
            45.401448117042904,
            -75.63689143645685
          ],
          "min order - 20.0"
        ],
        "2.0": [
          [
            45.40081723437033,
            -75.61136263719091
          ],
          "min order - 20.0"
        ]
      },
      "112": {
        "0": [
          [
            45.40270759999999,
            -75.68795
          ]
        ],
        "0.4": [
          [
            45.4013592641445,
            -75.6832130911133
          ],
          "min order - 20.0"
        ],
        "0.8": [
          [
            45.39866239505973,
            -75.67373972401361
          ],
          "min order - 20.0"
        ],
        "1.2000000000000002": [
          [
            45.394616794500116,
            -75.65953068727096
          ],
          "min order - 20.0"
        ],
        "1.6": [
          [
            45.38922226340317,
            -75.64058710713016
          ],
          "min order - 20.0"
        ],
        "2.0": [
          [
            45.38247860194434,
            -75.61691044716983
          ],
          "min order - 20.0"
        ]
      },
      "132": {
        "0": [
          [
            45.40270760000001,
            -75.68795
          ]
        ],
        "0.4": [
          [
            45.400299284712375,
            -75.6841534029319
          ],
          "min order - 20.0"
        ],
        "0.8": [
          [
            45.39548252491651,
            -75.676560853898
          ],
          "min order - 20.0"
        ],
        "1.2000000000000002": [
          [
            45.388257188432306,
            -75.66517348140626
          ],
          "min order - 20.0"
        ],
        "1.6": [
          [
            45.37862314018297,
            -75.64999289667065
          ],
          "min order - 20.0"
        ],
        "2.0": [
          [
            45.36658024225778,
            -75.63102119260691
          ],
          "min order - 20.0"
        ],
        "2.4": [
          [
            45.3521283539747,
            -75.60826094252458
          ],
          "min order - 20.0"
        ]
      }
    }
  },
  {
    "0": {
      "144": {
        "0": [
          [
            45.4027076,
            -75.68795
          ]
        ],
        "0.4": [
          [
            45.3997958464074,
            -75.68494713451477
          ],
          "min order - 20.0"
        ],
        "0.8": [
          [
            45.39397225583012,
            -75.6789420204096
          ],
          "min order - 20.0"
        ],
        "1.2000000000000002": [
          [
            45.385236740479264,
            -75.66993573668819
          ],
          "min order - 20.0"
        ],
        "1.6": [
          [
            45.37358920821664,
            -75.65792982366179
          ],
          "min order - 20.0"
        ],
        "2.0": [
          [
            45.359029562602025,
            -75.6429262817664
          ],
          "min order - 20.0"
        ],
        "2.4": [
          [
            45.34155770294041,
            -75.62492757003004
          ],
          "min order - 20.0"
        ]
      },
      "164": {
        "0": [
          [
            45.40270760000001,
            -75.68795
          ]
        ],
        "0.4": [
          [
            45.399247936693364,
            -75.68654184302602
          ],
          "min order - 20.0"
        ],
        "0.8": [
          [
            45.39232858641246,
            -75.68372587276464
          ],
          "min order - 20.0"
        ],
        "1.2000000000000002": [
          [
            45.381949519195416,
            -75.6795026903195
          ],
          "min order - 20.0"
        ],
        "1.6": [
          [
            45.368110698798304,
            -75.67387315365207
          ],
          "min order - 20.0"
        ],
        "2.0": [
          [
            45.35081208270738,
            -75.66683837678988
          ],
          "min order - 20.0"
        ]
      },
      "184": {
        "0": [
          [
            45.402707600000014,
            -75.68795
          ]
        ],
        "0.4": [
          [
            45.399117289816886,
            -75.68830636620555
          ],
          "min order - 20.0"
        ],
        "0.8": [
          [
            45.39193666153936,
            -75.6890190083555
          ],
          "min order - 20.0"
        ],
        "1.2000000000000002": [
          [
            45.381165700457565,
            -75.69008776858809
          ],
          "min order - 20.0"
        ],
        "1.6": [
          [
            45.36680438506365,
            -75.6915124215938
          ],
          "min order - 20.0"
        ],
        "2.0": [
          [
            45.3488526870524,
            -75.69329267483158
          ],
          "min order - 20.0"
        ]
      },
      "204": {
        "0": [
          [
            45.402707600000014,
            -75.68795
          ]
        ],
        "0.4": [
          [
            45.39941966092635,
            -75.69002791419939
          ],
          "min order - 20.0"
        ],
        "0.8": [
          [
            45.39284373928851,
            -75.69418326061052
          ],
          "min order - 20.0"
        ],
        "1.2000000000000002": [
          [
            45.38297978593407,
            -75.70041519621513
          ],
          "min order - 20.0"
        ],
        "1.6": [
          [
            45.369827746074336,
            -75.70872251770663
          ],
          "min order - 20.0"
        ],
        "2.0": [
          [
            45.35338755930979,
            -75.71910366254224
          ],
          "min order - 20.0"
        ],
        "2.4": [
          [
            45.33365915965537,
            -75.73155671030374
          ],
          "min order - 20.0"
        ]
      }
    }
  },
  {
    "0": {
      "216": {
        "0": [
          [
            45.4027076,
            -75.68795
          ]
        ],
        "0.4": [
          [
            45.3997958464074,
            -75.69095286548523
          ],
          "min order - 20.0"
        ],
        "0.8": [
          [
            45.39397225583012,
            -75.69695797959041
          ],
          "min order - 20.0"
        ],
        "1.2000000000000002": [
          [
            45.385236740479264,
            -75.70596426331181
          ],
          "min order - 20.0"
        ],
        "1.6": [
          [
            45.37358920821664,
            -75.71797017633821
          ],
          "min order - 20.0"
        ],
        "2.0": [
          [
            45.359029562602025,
            -75.7329737182336
          ],
          "min order - 20.0"
        ],
        "2.4": [
          [
            45.34155770294041,
            -75.75097242996996
          ],
          "min order - 20.0"
        ]
      },
      "236": {
        "0": [
          [
            45.40270760000001,
            -75.68795
          ]
        ],
        "0.4": [
          [
            45.40069494354747,
            -75.69218543766763
          ],
          "min order - 20.0"
        ],
        "0.8": [
          [
            45.39666947148714,
            -75.70065571154426
          ],
          "min order - 20.0"
        ],
        "1.2000000000000002": [
          [
            45.39063102263093,
            -75.71335976938354
          ],
          "min order - 20.0"
        ],
        "1.6": [
          [
            45.382579433823494,
            -75.73029610867614
          ],
          "min order - 20.0"
        ],
        "2.0": [
          [
            45.372514540007415,
            -75.75146277741199
          ],
          "min order - 20.0"
        ],
        "2.4": [
          [
            45.36043617428847,
            -75.7768573750797
          ],
          "min order - 20.0"
        ],
        "2.8": [
          [
            45.34634416800065,
            -75.80647705390209
          ],
          "min order - 20.0"
        ]
      },
      "256": {
        "0": [
          [
            45.402707600000014,
            -75.68795
          ]
        ],
        "0.4": [
          [
            45.40183679715641,
            -75.69290720578597
          ],
          "min order - 20.0"
        ],
        "0.8": [
          [
            45.40009497594983,
            -75.7028213127409
          ],
          "min order - 20.0"
        ],
        "1.2000000000000002": [
          [
            45.397481920522566,
            -75.71769178778308
          ],
          "min order - 20.0"
        ],
        "1.6": [
          [
            45.3939974147175,
            -75.73751786941638
          ],
          "min order - 20.0"
        ],
        "2.0": [
          [
            45.38964124211687,
            -75.7622985678326
          ],
          "min order - 20.0"
        ]
      },
      "276": {
        "0": [
          [
            45.40270760000001,
            -75.68795
          ]
        ],
        "0.4": [
          [
            45.40308369282313,
            -75.69303108817705
          ],
          "min order - 20.0"
        ],
        "0.8": [
          [
            45.40383565235991,
            -75.70319339936599
          ],
          "min order - 20.0"
        ],
        "1.2000000000000002": [
          [
            45.40496325239826,
            -75.71843716945656
          ],
          "min order - 20.0"
        ],
        "1.6": [
          [
            45.406466266605904,
            -75.73876273533628
          ],
          "min order - 20.0"
        ]
      }
    }
  },
  {
    "0": {
      "288": {
        "0": [
          [
            45.4027076,
            -75.68795
          ]
        ],
        "0.4": [
          [
            45.40381967208289,
            -75.69280908333285
          ],
          "min order - 20.0"
        ],
        "0.8": [
          [
            45.40604360886611,
            -75.70252763133581
          ],
          "min order - 20.0"
        ],
        "1.2000000000000002": [
          [
            45.40937920223899,
            -75.71710631139852
          ],
          "min order - 20.0"
        ]
      },
      "308": {
        "0": [
          [
            45.40270760000001,
            -75.68795
          ]
        ],
        "0.4": [
          [
            45.40492334084518,
            -75.69197613767987
          ],
          "min order - 20.0"
        ],
        "0.8": [
          [
            45.409354677999985,
            -75.70002904266559
          ],
          "min order - 20.0"
        ],
        "1.2000000000000002": [
          [
            45.41600146423546,
            -75.71210981717023
          ],
          "min order - 20.0"
        ]
      },
      "328": {
        "0": [
          [
            45.402707600000014,
            -75.68795
          ]
        ],
        "0.4": [
          [
            45.40575975635535,
            -75.69065752574306
          ],
          "min order - 20.0"
        ],
        "0.8": [
          [
            45.41186399995294,
            -75.69607316052559
          ],
          "min order - 20.0"
        ],
        "1.2000000000000002": [
          [
            45.42102025670107,
            -75.70419792562714
          ],
          "min order - 20.0"
        ]
      },
      "348": {
        "0": [
          [
            45.402707600000014,
            -75.68795
          ]
        ],
        "0.4": [
          [
            45.40622802119381,
            -75.68901229560593
          ],
          "min order - 20.0"
        ],
        "0.8": [
          [
            45.41326884716064,
            -75.69113715079646
          ],
          "min order - 20.0"
        ],
        "1.2000000000000002": [
          [
            45.423830054930654,
            -75.69432502780695
          ],
          "min order - 20.0"
        ]
      }
    }
  }
]